gas_price.py
gasprice_blocklytics-0.0.1.dist-info/METADATA
gasprice_blocklytics-0.0.1.dist-info/WHEEL
gasprice_blocklytics-0.0.1.dist-info/entry_points.txt
gasprice_blocklytics-0.0.1.dist-info/top_level.txt
gasprice_blocklytics-0.0.1.dist-info/RECORD
